ShiftRegister.v
// without shift enable
module ShiftRegister(
  input wire clk, 
  input wire reset,
  input wire direction, // 0 for right, 1 for left
  input wire in,
  output wire [3:0] out
);

  reg [3:0] register;

  always @(posedge clk or posedge reset) begin
    if (reset) begin
      register <= 4'b0000;
    end
    else begin
      // left shift
      if (direction) begin
        register <= {register[2:0], in};
      end
      else begin
        register <= {in, register[3:1]};
      end
    end
  end

  assign out = register;

endmodule

module ShiftRegisterTB;
  reg clk, reset, direction, in;
  wire [3:0] out;

  ShiftRegister sr(
    .clk(clk),
    .reset(reset),
    .direction(direction),
    .in(in),
    .out(out)
  );

  initial begin
    clk = 0;
    forever #5 clk = ~clk;
  end

  initial begin
    $dumpfile("ShiftRegister.vcd");
    $dumpvars;

    reset = 1;
    direction = 0;
    in = 0;
    #15;
    reset = 0;

    // test 1010, right shift
    direction = 0;
    
    in = 1; #10;
    in = 0; #10;
    in = 1; #10;
    in = 0; #10;

    // test 0101, left shift
    direction = 1;
    
    in = 0; #10;
    in = 1; #10;
    in = 0; #10;
    in = 1; #10;
    $finish;
  end

endmodule

ShiftRegister.vcd
$date
	Tue Apr 22 13:07:08 2025
$end
$version
	Icarus Verilog
$end
$timescale
	1s
$end
$scope module ShiftRegisterTB $end
$var wire 4 ! out [3:0] $end
$var reg 1 " clk $end
$var reg 1 # direction $end
$var reg 1 $ in $end
$var reg 1 % reset $end
$scope module sr $end
$var wire 1 " clk $end
$var wire 1 # direction $end
$var wire 1 $ in $end
$var wire 4 & out [3:0] $end
$var wire 1 % reset $end
$var reg 4 ' register [3:0] $end
$upscope $end
$upscope $end
$enddefinitions $end
$comment Show the parameter values. $end
$dumpall
$end
#0
$dumpvars
b0 '
b0 &
1%
0$
0#
0"
b0 !
$end
#5
1"
#10
0"
#15
b1000 !
b1000 &
b1000 '
1"
1$
0%
#20
0"
#25
b100 !
b100 &
b100 '
1"
0$
#30
0"
#35
b1010 !
b1010 &
b1010 '
1"
1$
#40
0"
#45
b101 !
b101 &
b101 '
1"
0$
#50
0"
#55
b1010 !
b1010 &
b1010 '
1"
1#
#60
0"
#65
b101 !
b101 &
b101 '
1"
1$
#70
0"
#75
b1010 !
b1010 &
b1010 '
1"
0$
#80
0"
#85
b101 !
b101 &
b101 '
1"
1$
#90
0"
#95
b1011 !
b1011 &
b1011 '
1"
